Metadata-Version: 1.0
Name: rwgpapi
Version: 0.1
Summary: A fork of https://github.com/NoMore201/googleplay-api with some enhancements.
Home-page: https://github.com/rehmatworks/googleplay-api
Author: Rehmat
Author-email: contact@rehmat.works
License: GPL3
Platform: UNKNOWN
